smithery/__init__.py
smithery/cli/__init__.py
smithery/cli/dev.py
smithery/cli/init.py
smithery/cli/main.py
smithery/cli/playground.py
smithery/cli/start.py
smithery/decorators.py
smithery/py.typed
smithery/server/__init__.py
smithery/server/fastmcp_patch.py
smithery/server/middleware.py
smithery/utils/__init__.py
smithery/utils/config.py
smithery/utils/console.py
smithery/utils/network.py
smithery/utils/project.py
smithery/utils/responses.py
smithery/utils/server.py
smithery/utils/url.py
smithery-0.4.4.dist-info/WHEEL
smithery-0.4.4.dist-info/entry_points.txt
smithery-0.4.4.dist-info/METADATA
smithery-0.4.4.dist-info/RECORD
