Metadata-Version: 2.4
Name: smithery
Version: 0.4.4
Summary: SDK for using Smithery with Python
Author: Smithery Team
Author-email: Smithery Team <contact@smithery.ai>
License-Expression: MIT
Classifier: Operating System :: OS Independent
Requires-Dist: toml>=0.10.2
Requires-Dist: tomli>=2.0.0 ; python_full_version < '3.11'
Requires-Dist: typer>=0.17.3
Requires-Dist: art>=6.3
Requires-Dist: uvicorn>=0.30.0
Requires-Dist: pydantic>=2.0.0
Requires-Dist: starlette>=0.37.0
Requires-Dist: mcp>=1.6.0 ; extra == 'fastmcp'
Requires-Dist: fastmcp>=2.0.0 ; extra == 'fastmcp'
Requires-Python: >=3.10
Project-URL: Bug Tracker, https://github.com/smithery-ai/python-sdk/issues
Project-URL: Homepage, https://github.com/smithery-ai/python-sdk
Provides-Extra: fastmcp
